django_autoslugfield/__init__.py
django_autoslugfield/fields.py
django_autoslugfield/utils.py
django_easy_autoslug-1.0.4.dist-info/AUTHORS
django_easy_autoslug-1.0.4.dist-info/LICENSE
django_easy_autoslug-1.0.4.dist-info/METADATA
django_easy_autoslug-1.0.4.dist-info/WHEEL
django_easy_autoslug-1.0.4.dist-info/top_level.txt
django_easy_autoslug-1.0.4.dist-info/RECORD
