Metadata-Version: 2.1
Name: django-easy-autoslug
Version: 1.0.4
Summary: Automatic slug for django
Author-email: Miroslav Bendík <miroslav.bendik@gmail.com>
License: MIT
Project-URL: homepage, https://github.com/mireq/django-autoslugfield
Project-URL: documentation, https://github.com/mireq/django-autoslugfield
Project-URL: repository, https://github.com/mireq/django-autoslugfield
Project-URL: changelog, https://github.com/mireq/django-autoslugfield/blob/master/CHANGELOG.md
Keywords: slug,django
Classifier: Programming Language :: Python :: 3
Requires-Python: >=3.7
License-File: LICENSE
License-File: AUTHORS
Requires-Dist: django
Provides-Extra: dev
Requires-Dist: tox ; extra == 'dev'
Requires-Dist: pylint ; extra == 'dev'
Requires-Dist: pre-commit ; extra == 'dev'
Requires-Dist: bump2version ; extra == 'dev'
Requires-Dist: commitizen ; extra == 'dev'
